setup.py
datalabsdk/DataTransform.py
datalabsdk/DataType.py
datalabsdk/Model.py
datalabsdk/__init__.py
datalabsdk.egg-info/PKG-INFO
datalabsdk.egg-info/SOURCES.txt
datalabsdk.egg-info/dependency_links.txt
datalabsdk.egg-info/requires.txt
datalabsdk.egg-info/top_level.txt