Metadata-Version: 1.1
Name: datalabsdk
Version: 0.1.6
Summary: Data Lab API for Python
Home-page: https://github.com/patrickyeh/datalabsdk-python
Author: III Data Analytic Team
Author-email: patrickyeh@iii.org.tw
License: UNKNOWN
Platform: UNKNOWN
Classifier: Development Status :: 3 - Alpha
Classifier: Intended Audience :: Developers
Classifier: Operating System :: OS Independent
Classifier: Programming Language :: Python
Classifier: Programming Language :: Python :: 2
Classifier: Programming Language :: Python :: 2.6
Classifier: Programming Language :: Python :: 2.7
